apdocc/__init__.py
apdocc/colors.json
apdocc/combinations.json
apdocc/io.py
apdocc/models.py
apdocc/py.typed
apdocc/rich_view.py
apdocc/svg_export.py
apdocc/utils/__init__.py
apdocc/utils/config.py
apdocc/utils/logger.py
apdocc-0.2.0.dist-info/METADATA
apdocc-0.2.0.dist-info/WHEEL
apdocc-0.2.0.dist-info/licenses/LICENSE
apdocc-0.2.0.dist-info/RECORD
