Metadata-Version: 2.4
Name: apdocc
Version: 0.2.0
Summary: A Python Dictionary of Color Combinations
Author-email: Thomas Camminady <0milieux_member@icloud.com>
License-File: LICENSE
Requires-Python: >=3.8
Requires-Dist: rich>=10.0.0
